qt_custom/__init__.py
qt_custom/custom_listview.cp310-win_amd64.pyd
qt_custom/custom_listview.cp311-win_amd64.pyd
qt_custom/custom_listview.cp312-win_amd64.pyd
qt_custom/custom_listview.cp313-win_amd64.pyd
qt_custom/custom_listview.cp37-win_amd64.pyd
qt_custom/custom_listview.cp38-win_amd64.pyd
qt_custom/custom_listview.cp39-win_amd64.pyd
qt_custom/custom_menubar.cp310-win_amd64.pyd
qt_custom/custom_menubar.cp311-win_amd64.pyd
qt_custom/custom_menubar.cp312-win_amd64.pyd
qt_custom/custom_menubar.cp313-win_amd64.pyd
qt_custom/custom_menubar.cp37-win_amd64.pyd
qt_custom/custom_menubar.cp38-win_amd64.pyd
qt_custom/custom_menubar.cp39-win_amd64.pyd
qt_custom/custom_tab.cp310-win_amd64.pyd
qt_custom/custom_tab.cp311-win_amd64.pyd
qt_custom/custom_tab.cp312-win_amd64.pyd
qt_custom/custom_tab.cp313-win_amd64.pyd
qt_custom/custom_tab.cp37-win_amd64.pyd
qt_custom/custom_tab.cp38-win_amd64.pyd
qt_custom/custom_tab.cp39-win_amd64.pyd
qt_custom/custom_tableview.cp310-win_amd64.pyd
qt_custom/custom_tableview.cp311-win_amd64.pyd
qt_custom/custom_tableview.cp312-win_amd64.pyd
qt_custom/custom_tableview.cp313-win_amd64.pyd
qt_custom/custom_tableview.cp37-win_amd64.pyd
qt_custom/custom_tableview.cp38-win_amd64.pyd
qt_custom/custom_tableview.cp39-win_amd64.pyd
qt_custom/custom_treeview.cp310-win_amd64.pyd
qt_custom/custom_treeview.cp311-win_amd64.pyd
qt_custom/custom_treeview.cp312-win_amd64.pyd
qt_custom/custom_treeview.cp313-win_amd64.pyd
qt_custom/custom_treeview.cp37-win_amd64.pyd
qt_custom/custom_treeview.cp38-win_amd64.pyd
qt_custom/custom_treeview.cp39-win_amd64.pyd
qt_custom/logger_qt_custom.cp310-win_amd64.pyd
qt_custom/logger_qt_custom.cp311-win_amd64.pyd
qt_custom/logger_qt_custom.cp312-win_amd64.pyd
qt_custom/logger_qt_custom.cp313-win_amd64.pyd
qt_custom/logger_qt_custom.cp37-win_amd64.pyd
qt_custom/logger_qt_custom.cp38-win_amd64.pyd
qt_custom/logger_qt_custom.cp39-win_amd64.pyd
qt_custom/chart/__init__.py
qt_custom/chart/custom_chart.cp310-win_amd64.pyd
qt_custom-0.2.19.dist-info/licenses/LICENSE.txt
qt_custom-0.2.19.dist-info/METADATA
qt_custom-0.2.19.dist-info/WHEEL
qt_custom-0.2.19.dist-info/top_level.txt
qt_custom-0.2.19.dist-info/RECORD
