Metadata-Version: 2.4
Name: qt-custom
Version: 0.2.19
Summary: Customized Qt Classes
Home-page: https://github.com/pypa/sampleproject
Author: anonymous
Author-email: anonymous@gmail.com
Project-URL: Bug Tracker, https://github.com/pypa/sampleproject/issues
Classifier: Programming Language :: Python :: 3
Classifier: License :: OSI Approved :: MIT License
Classifier: Operating System :: OS Independent
Requires-Python: >=3.7
License-File: LICENSE.txt
Dynamic: license-file
